{
    "version": "1.5.4-beta.66",
    "description": "A new cross-platform Apple Music experience based on Electron and Vue.js written from scratch with performance in mind.",
    "homepage": "https://cider.sh",
    "license": {
        "identifier": "AGPL-3.0-or-later",
        "url": "https://github.com/ciderapp/Cider/blob/main/LICENSE"
    },
    "architecture": {
        "64bit": {
            "url": "https://github.com/ciderapp/cider-releases/releases/download/v1.5.4-beta.66/Cider-Setup-1.5.4-beta.66.exe#/dl.7z",
            "hash": "sha512:2d8f3161c79ac2a7ceaa5decc25d26bad010573aa55a7672cea1349ae38ea0d4a631ffbecae8dc7b919074ed5e6c45903bcde1e44f285acf276f6b318bf9074c",
            "pre_install": "Expand-7zipArchive \"$dir\\`$PLUGINSDIR\\app-64.7z\" \"$dir\" -Removal"
        }
    },
    "post_install": "Remove-Item \"$dir\\`$PLUGINSDIR\", \"$dir\\`$R0\" -Recurse -Force",
    "shortcuts": [
        [
            "Cider.exe",
            "Cider",
            "--user-data-dir=\"$dir\\User Data\""
        ]
    ],
    "persist": "User Data",
    "checkver": {
        "url": "https://api.github.com/repos/ciderapp/cider-releases/releases",
        "jsonpath": "$[0].tag_name",
        "regex": "v(.*)"
    },
    "autoupdate": {
        "architecture": {
            "64bit": {
                "url": "https://github.com/ciderapp/cider-releases/releases/download/v$version/Cider-Setup-$version.exe#/dl.7z",
                "hash": {
                    "url": "$baseurl/latest.yml",
                    "regex": "(?sm)$basename.*?sha512:\\s+$base64"
                }
            }
        }
    }
}
