{
    "version": "6.0.402",
    "description": "Microsoft .NET 6 SDK. The software development kit (SDK) includes everything you need to build and run .NET applications, using command-line tools and any editor (like Visual Studio).",
    "homepage": "https://dotnet.microsoft.com",
    "license": {
        "identifier": "MIT",
        "url": "https://github.com/dotnet/core/raw/main/LICENSE.TXT"
    },
    "architecture": {
        "64bit": {
            "url": "https://download.visualstudio.microsoft.com/download/pr/554fb42f-36ae-4f2f-b7e1-6b447ebb1867/a512568a4574fc3494b73c187a5316d8/dotnet-sdk-6.0.402-win-x64.zip",
            "hash": "sha512:609217ef0e1baecc250db94cf0a0255301220d8f6a443424c0bd912b07c1fdaa5eef89b28907a70e05bee5b76c4792afdbf3e5399dc609a41c05319e523b96dd"
        },
        "32bit": {
            "url": "https://download.visualstudio.microsoft.com/download/pr/d8acba56-9bae-4e67-bd33-b98df3f3600b/9f656456ea9f145e67b4322c1bccb15a/dotnet-sdk-6.0.402-win-x86.zip",
            "hash": "sha512:a00d256379cc9bda550c5eee632ac16bae6b3beb385efc9d22f5bbaf414405a27ce3f24ecef335ae3b470104f9a28ef0a89cbf87fede41e1d7493c83b8b209a8"
        }
    },
    "bin": "dotnet.exe",
    "env_add_path": ".",
    "env_set": {
        "DOTNET_ROOT": "$dir",
        "MSBuildSDKsPath": "$dir\\sdk\\$version\\Sdks"
    },
    "checkver": {
        "url": "https://dotnetcli.blob.core.windows.net/dotnet/release-metadata/6.0/releases.json",
        "jsonpath": "$.releases[0].sdk",
        "regex": "(?sm)version.*?([\\d.]+).*?runtime-version\": \"(?<runtimever>[\\d.]+).+download/pr/(?<x64>.*?-win-x64.zip).+download/pr/(?<x86>.*?-win-x86.zip)"
    },
    "autoupdate": {
        "architecture": {
            "64bit": {
                "url": "https://download.visualstudio.microsoft.com/download/pr/$matchX64"
            },
            "32bit": {
                "url": "https://download.visualstudio.microsoft.com/download/pr/$matchX86"
            }
        },
        "hash": {
            "url": "https://dotnetcli.blob.core.windows.net/dotnet/checksums/$matchRuntimever-sha.txt",
            "mode": "extract",
            "regex": "(?sm)$sha512\\s+$basename"
        }
    }
}
